rplidar_mqtt_bridge/__init__.py
rplidar_mqtt_bridge/bridge.py
rplidar_mqtt_bridge/main.py
rplidar_mqtt_bridge/parser.py
rplidar_mqtt_bridge/utils.py
rplidar_mqtt_bridge-0.0.1.dist-info/LICENSE
rplidar_mqtt_bridge-0.0.1.dist-info/METADATA
rplidar_mqtt_bridge-0.0.1.dist-info/WHEEL
rplidar_mqtt_bridge-0.0.1.dist-info/entry_points.txt
rplidar_mqtt_bridge-0.0.1.dist-info/top_level.txt
rplidar_mqtt_bridge-0.0.1.dist-info/RECORD
