Metadata-Version: 2.1
Name: rplidar-mqtt-bridge
Version: 0.0.1
Summary: A simple bridge between an RPLIDAR device and an MQTT Broker
Home-page: https://github.com/adaptant-labs/rplidar-mqtt-bridge
Author: Adaptant Labs
Author-email: labs@adaptant.io
License: Apache License 2.0
Keywords: rplidar lidar sensors mqtt
Platform: UNKNOWN
Classifier: Development Status :: 3 - Alpha
Classifier: Intended Audience :: Developers
Classifier: License :: OSI Approved :: Apache Software License
Classifier: Topic :: System :: Hardware
Classifier: Programming Language :: Python :: 3
Classifier: Topic :: Communications
Classifier: Topic :: Internet
Classifier: Topic :: Scientific/Engineering :: Interface Engine/Protocol Translator
Requires-Dist: rplidar
Requires-Dist: paho-mqtt
